xync_client/Proto.py
xync_client/__init__.py
xync_client/exceptions.py
xync_client/loader.py
xync_client/rs.py
xync_client/Binance/binance_async.py
xync_client/Binance/earn_api.py
xync_client/Binance/sapi.py
xync_client/Binance/web.py
xync_client/Binance/web_c2c.py
xync_client/Bybit/web_earn.py
xync_client/Bybit/web_p2p.py
xync_client/Gate/premarket.py
xync_client/Htx/web.py
xync_client/Htx/web_c2c.py
xync_client/Htx/watchdog/Ad.py
xync_client/Htx/watchdog/init.py
xync_client/Htx/watchdog/lib.py
xync_client/Htx/watchdog/main.py
xync_client/KuCoin/web.py
xync_client/Okx/web.py
xync_client/TgWallet/pyro.py
xync_client/TgWallet/web.py
xync_client/TgWallet/web_p2p.py
xync_client-0.1.3.dist-info/METADATA
xync_client-0.1.3.dist-info/WHEEL
xync_client-0.1.3.dist-info/top_level.txt
xync_client-0.1.3.dist-info/RECORD
