Metadata-Version: 2.1
Name: xync-client
Version: 0.1.3
Author-email: Mike Artemiev <mixartemev@gmail.com>
Project-URL: Homepage, https://gitlab.com/xync/back/cex-clients
Project-URL: Repository, https://gitlab.com/xync/back/cex-clients
Requires-Python: >=3.12
Requires-Dist: http-client-async
Requires-Dist: asynchuobi
Requires-Dist: python-binance
Requires-Dist: pybit
Requires-Dist: pyrogram
Requires-Dist: python-okx
Requires-Dist: xync-schema
Provides-Extra: dev
Requires-Dist: build ; extra == 'dev'
Requires-Dist: python-dotenv ; extra == 'dev'
Requires-Dist: pytest-asyncio ; extra == 'dev'
Requires-Dist: setuptools-scm ; extra == 'dev'
Requires-Dist: twine ; extra == 'dev'
